src/__init__.py
src/api.py
src/cli.py
src/main.py
src/profile.py
src/console/__init__.py
src/console/flexiblesearch.py
src/console/impex.py
src/console/scripting.py
sapcx-0.1.2.dist-info/LICENSE
sapcx-0.1.2.dist-info/METADATA
sapcx-0.1.2.dist-info/WHEEL
sapcx-0.1.2.dist-info/entry_points.txt
sapcx-0.1.2.dist-info/top_level.txt
sapcx-0.1.2.dist-info/RECORD
