Metadata-Version: 2.1
Name: sapcx
Version: 0.1.2
Summary: CLI Utility for SAP CX (Hybris) developers
Home-page: https://github.com/ablil/sapcx
Author: ablil
Author-email: ablil@protonmail.com
License: MIT
Requires-Python: >3.2
License-File: LICENSE
Requires-Dist: requests
Requires-Dist: urllib3
Requires-Dist: bs4
